liyanery/__init__.py
liyanery-0.2.9.dist-info/METADATA
liyanery-0.2.9.dist-info/WHEEL
liyanery-0.2.9.dist-info/RECORD
