Metadata-Version: 2.1
Name: liyanery
Version: 0.2.9
Summary: 
Author: Louis Zhuang
Author-email: yzhuang@outlook.com
Requires-Python: >=3.12,<4.0
Classifier: Programming Language :: Python :: 3
Classifier: Programming Language :: Python :: 3.12
Requires-Dist: dash-bootstrap-components (>=1.6.0,<2.0.0)
Requires-Dist: dash-bootstrap-templates (==1.1.2)
Requires-Dist: dash[celery,diskcache] (>=2.17.1,<3.0.0)
Requires-Dist: flask-caching (>=2.3.0,<3.0.0)
Requires-Dist: gunicorn (>=23.0.0,<24.0.0) ; sys_platform == "linux"
Requires-Dist: ib-insync (>=0.9.86,<0.10.0)
Requires-Dist: numpy (>=2.0.1,<3.0.0)
Requires-Dist: pandas (>=2.2.2,<3.0.0)
Requires-Dist: pyorbital (>=1.8.3,<2.0.0)
Requires-Dist: redis (>=5.0.7,<6.0.0)
